aiosmf/__init__.py
aiosmf/connection.py
aiosmf/constants.py
aiosmf/filter.py
aiosmf/util.py
aiosmf/smf/__init__.py
aiosmf/smf/rpc/__init__.py
aiosmf/smf/rpc/compression_flags.py
aiosmf/smf/rpc/dynamic_header.py
aiosmf/smf/rpc/header.py
aiosmf/smf/rpc/header_bit_flags.py
aiosmf/smf/rpc/null_type.py
aiosmf/smf/rpc/payload_headers.py
aiosmf-0.1.0.dist-info/LICENSE
aiosmf-0.1.0.dist-info/METADATA
aiosmf-0.1.0.dist-info/WHEEL
aiosmf-0.1.0.dist-info/top_level.txt
aiosmf-0.1.0.dist-info/zip-safe
aiosmf-0.1.0.dist-info/RECORD
