Metadata-Version: 2.1
Name: aiosmf
Version: 0.1.0
Summary: Python asyncio smf rpc implementation
Home-page: https://github.com/noahdesu/aiosmf
Author: Noah Watkins
Author-email: noahwatkins@gmail.com
License: Apache License 2.0
Keywords: smf rpc seastar
Platform: UNKNOWN
Classifier: Framework :: AsyncIO
Classifier: Intended Audience :: Developers
Classifier: Topic :: System :: Networking
Classifier: Development Status :: 4 - Beta
Classifier: Operating System :: POSIX
Classifier: Programming Language :: Python :: 3.7
Classifier: License :: OSI Approved :: Apache Software License
Requires-Python: >=3.7
Requires-Dist: flatbuffers (>=1.10)
Requires-Dist: xxhash (>=1.3.0)
Requires-Dist: zstandard (>=0.11.0)
